odoo/addons/fieldservice_stock/README.rst
odoo/addons/fieldservice_stock/__init__.py
odoo/addons/fieldservice_stock/__manifest__.py
odoo/addons/fieldservice_stock/data/fsm_stock_data.xml
odoo/addons/fieldservice_stock/models/__init__.py
odoo/addons/fieldservice_stock/models/fsm_equipment.py
odoo/addons/fieldservice_stock/models/fsm_location.py
odoo/addons/fieldservice_stock/models/fsm_order.py
odoo/addons/fieldservice_stock/models/product_template.py
odoo/addons/fieldservice_stock/models/stock.py
odoo/addons/fieldservice_stock/models/stock_production_lot.py
odoo/addons/fieldservice_stock/readme/CONFIGURE.rst
odoo/addons/fieldservice_stock/readme/CONTRIBUTORS.rst
odoo/addons/fieldservice_stock/readme/CREDITS.rst
odoo/addons/fieldservice_stock/readme/DESCRIPTION.rst
odoo/addons/fieldservice_stock/readme/INSTALL.rst
odoo/addons/fieldservice_stock/readme/ROADMAP.rst
odoo/addons/fieldservice_stock/readme/USAGE.rst
odoo/addons/fieldservice_stock/security/ir.model.access.csv
odoo/addons/fieldservice_stock/static/description/icon.png
odoo/addons/fieldservice_stock/static/description/index.html
odoo/addons/fieldservice_stock/views/fsm_equipment.xml
odoo/addons/fieldservice_stock/views/fsm_location.xml
odoo/addons/fieldservice_stock/views/fsm_order.xml
odoo/addons/fieldservice_stock/views/product_template.xml
odoo/addons/fieldservice_stock/views/stock.xml
odoo/addons/fieldservice_stock/views/stock_production_lot.xml
odoo11_addon_fieldservice_stock-11.0.0.2.0.dist-info/METADATA
odoo11_addon_fieldservice_stock-11.0.0.2.0.dist-info/RECORD
odoo11_addon_fieldservice_stock-11.0.0.2.0.dist-info/WHEEL
odoo11_addon_fieldservice_stock-11.0.0.2.0.dist-info/top_level.txt
